pythaiidcard/__init__.py
pythaiidcard/cli.py
pythaiidcard/constants.py
pythaiidcard/exceptions.py
pythaiidcard/models.py
pythaiidcard/reader.py
pythaiidcard/system_check.py
pythaiidcard/utils.py
pythaiidcard-0.3.0.dist-info/METADATA
pythaiidcard-0.3.0.dist-info/WHEEL
pythaiidcard-0.3.0.dist-info/entry_points.txt
pythaiidcard-0.3.0.dist-info/licenses/LICENSE
pythaiidcard-0.3.0.dist-info/RECORD
