Metadata-Version: 2.4
Name: pythaiidcard
Version: 0.3.0
Summary: Python library for reading Thai national ID cards using smartcard readers
Project-URL: Homepage, https://github.com/ninyawee/pythaiidcard
Project-URL: Documentation, https://github.com/ninyawee/pythaiidcard#readme
Project-URL: Repository, https://github.com/ninyawee/pythaiidcard
Project-URL: Issue Tracker, https://github.com/ninyawee/pythaiidcard/issues
Author-email: Ninyawee <ninyawee@users.noreply.github.com>
License: ISC
License-File: LICENSE
Keywords: citizen-id,id-card,national-id,pcsc,smartcard,thai,thailand
Classifier: Development Status :: 4 - Beta
Classifier: Intended Audience :: Developers
Classifier: License :: OSI Approved :: ISC License (ISCL)
Classifier: Operating System :: POSIX :: Linux
Classifier: Programming Language :: Python :: 3
Classifier: Programming Language :: Python :: 3.13
Classifier: Programming Language :: Python :: 3.14
Classifier: Topic :: Security
Classifier: Topic :: Software Development :: Libraries :: Python Modules
Classifier: Topic :: System :: Hardware
Requires-Python: >=3.13
Requires-Dist: pillow>=11.3.0
Requires-Dist: pydantic>=2.0
Requires-Dist: pyscard>=2.3.0
Requires-Dist: python-dateutil>=2.8.2
Requires-Dist: typer[all]>=0.9.0
